proximal_energy/__init__.py
proximal_energy/api_client.py
proximal_energy-0.0.1.dist-info/METADATA
proximal_energy-0.0.1.dist-info/WHEEL
proximal_energy-0.0.1.dist-info/RECORD
