Metadata-Version: 2.1
Name: proximal-energy
Version: 0.0.1
Requires-Dist: python-dotenv
Requires-Dist: requests
